qjdltools/__init__.py
qjdltools/abandoned.py
qjdltools/distributed.py
qjdltools/dlbasic.py
qjdltools/dldata.py
qjdltools/dlimage.py
qjdltools/dlsetup.py
qjdltools/dltrain.py
qjdltools/fileop.py
qjdltools/gdal_utils.py
qjdltools/ptutils.py
qjdltools/transform.py
qjdltools-0.5.0.dist-info/LICENSE
qjdltools-0.5.0.dist-info/METADATA
qjdltools-0.5.0.dist-info/WHEEL
qjdltools-0.5.0.dist-info/top_level.txt
qjdltools-0.5.0.dist-info/RECORD
