Metadata-Version: 2.1
Name: qjdltools
Version: 0.5.0
Summary: Some simple tools for deep learning.
Home-page: https://github.com/ErenTuring/dl_tools
Author: Ji Qi
Author-email: 51978200@qq.com
License: MIT
Platform: UNKNOWN
Classifier: Intended Audience :: Developers
Classifier: Operating System :: OS Independent
Classifier: Programming Language :: Python
Classifier: Programming Language :: Python :: 3.5
Classifier: Programming Language :: Python :: 3.6
Classifier: Programming Language :: Python :: 3.7
Classifier: Programming Language :: Python :: 3.8
Classifier: Programming Language :: Python :: 3.9
License-File: LICENSE
Requires-Dist: matplotlib
Requires-Dist: opencv-python
Requires-Dist: tqdm
Requires-Dist: scikit-image
Requires-Dist: albumentations
